{
  "id": "1",
  "name": "Modern Professional",
  "category": "modern",
  "version": "1.0",
  "description": "Clean and contemporary design perfect for corporate roles",
  "author": "OPPZ ResumeAI",
  "createdAt": "2024-01-15",
  "updatedAt": "2024-01-15",
  "settings": {
    "primaryColor": "#2563eb",
    "secondaryColor": "#7c3aed",
    "accentColor": "#059669",
    "textColor": "#1f2937",
    "backgroundColor": "#ffffff",
    "fontFamily": "Inter, sans-serif",
    "fontSize": "14px",
    "lineHeight": "1.6"
  },
  "sections": {
    "header": {
      "enabled": true,
      "order": 1,
      "style": {
        "backgroundColor": "#2563eb",
        "color": "#ffffff",
        "padding": "2rem",
        "textAlign": "center"
      },
      "fields": [
        "name",
        "title",
        "contact",
        "summary"
      ]
    },
    "experience": {
      "enabled": true,
      "order": 2,
      "style": {
        "margin": "2rem 0",
        "padding": "0 2rem"
      },
      "fields": [
        "company",
        "position",
        "duration",
        "description"
      ]
    },
    "education": {
      "enabled": true,
      "order": 3,
      "style": {
        "margin": "2rem 0",
        "padding": "0 2rem"
      },
      "fields": [
        "institution",
        "degree",
        "year",
        "gpa"
      ]
    },
    "skills": {
      "enabled": true,
      "order": 4,
      "style": {
        "margin": "2rem 0",
        "padding": "0 2rem"
      },
      "fields": [
        "skillName",
        "proficiency"
      ]
    },
    "projects": {
      "enabled": true,
      "order": 5,
      "style": {
        "margin": "2rem 0",
        "padding": "0 2rem"
      },
      "fields": [
        "projectName",
        "description",
        "technologies",
        "link"
      ]
    }
  },
  "layout": {
    "type": "single-column",
    "maxWidth": "800px",
    "margin": "0 auto",
    "padding": "0"
  },
  "features": [
    "ATS Friendly",
    "Customizable Colors",
    "Professional Layout",
    "Print Ready",
    "Responsive Design",
    "Clean Typography"
  ],
  "formats": [
    "PDF",
    "DOCX",
    "HTML"
  ],
  "preview": {
    "image": "templates/assets/previews/professional-blue.png",
    "thumbnail": "templates/assets/previews/professional-blue.png"
  },
  "css": {
    "file": "templates/assets/styles/professional-blue.css",
    "variables": {
      "--primary-color": "#2563eb",
      "--secondary-color": "#7c3aed",
      "--accent-color": "#059669",
      "--text-color": "#1f2937",
      "--bg-color": "#ffffff"
    }
  }
}